{
  "model": "FeaturedMoE_N3",
  "dataset": "retail_rocket",
  "dataset_raw": "retail_rocket",
  "max_evals": 1,
  "oom_retry_limit": 0,
  "tune_epochs": 100,
  "n_completed": 1,
  "n_recorded_trials": 1,
  "timestamp": "2026-05-07T18:18:08.307351",
  "trials": [
    {
      "trial": 1,
      "params": {},
      "mrr@20": 0.3683,
      "valid_result": {
        "recall@10": 0.5687,
        "recall@20": 0.6457,
        "mrr@10": 0.363,
        "mrr@20": 0.3683,
        "ndcg@10": 0.4121,
        "ndcg@20": 0.4316,
        "hit@10": 0.5687,
        "hit@20": 0.6457,
        "precision@10": 0.0569,
        "precision@20": 0.0323
      },
      "test_result": {
        "recall@10": 0.5565,
        "recall@20": 0.6284,
        "mrr@10": 0.361,
        "mrr@20": 0.3659,
        "ndcg@10": 0.4078,
        "ndcg@20": 0.426,
        "hit@10": 0.5565,
        "hit@20": 0.6284,
        "precision@10": 0.0556,
        "precision@20": 0.0314
      },
      "valid_main_eval_filter": {
        "total_targets": 21584,
        "seen_targets": 19289,
        "unseen_targets": 2295,
        "dropped_eval_rows": 2295,
        "enabled": true
      },
      "test_main_eval_filter": {
        "total_targets": 20980,
        "seen_targets": 17672,
        "unseen_targets": 3308,
        "dropped_eval_rows": 3308,
        "enabled": true
      },
      "valid_cold_target_metrics": {
        "count": 2295,
        "hit@5": 0.009586056644880174,
        "hit@10": 0.022657952069716776,
        "hit@20": 0.0318082788671024,
        "ndcg@5": 0.004148980916715136,
        "ndcg@10": 0.00840733669422291,
        "ndcg@20": 0.010717877894964613,
        "mrr@5": 0.002432825025130461,
        "mrr@10": 0.004208251291760172,
        "mrr@20": 0.004840319267674988
      },
      "test_cold_target_metrics": {
        "count": 3308,
        "hit@5": 0.007859733978234583,
        "hit@10": 0.013603385731559855,
        "hit@20": 0.021463119709794438,
        "ndcg@5": 0.003660150575017987,
        "ndcg@10": 0.005494603330884332,
        "ndcg@20": 0.007467940850622565,
        "mrr@5": 0.0023125755986899248,
        "mrr@10": 0.0030566832161043403,
        "mrr@20": 0.0035905677931070182
      },
      "best_hr@10": 0.5687,
      "test_mrr@20": 0.3659,
      "test_hr@10": 0.5565,
      "epochs_run": 20,
      "early_stop_epoch": 20,
      "early_stopped": true,
      "elapsed": 1083.0,
      "avg_epoch_time_sec": 53.91771895885468,
      "avg_epoch_per_hour": 66.76840321726532,
      "test_eval_time_sec": 2.0558948516845703,
      "test_eval_batches": 11,
      "test_eval_targets": 20980,
      "test_eval_batches_per_sec": 5.350468187118986,
      "test_eval_targets_per_sec": 10204.802051432394,
      "oom_retry_count": 0,
      "oom_retry_history": [],
      "effective_train_batch_size": 2048,
      "effective_eval_batch_size": 2048,
      "status": "ok",
      "transfer_report": {
        "enabled": true,
        "mode": "full_model",
        "requested_mode": "full_model",
        "loaded_tensors": 294,
        "loaded_tensor_names_sample": [
          "input_ln.bias",
          "input_ln.weight",
          "position_embedding.weight",
          "stage_executor.attn_blocks.0.dense.bias",
          "stage_executor.attn_blocks.0.dense.weight",
          "stage_executor.attn_blocks.0.key.bias",
          "stage_executor.attn_blocks.0.key.weight",
          "stage_executor.attn_blocks.0.layer_norm.bias",
          "stage_executor.attn_blocks.0.layer_norm.weight",
          "stage_executor.attn_blocks.0.query.bias",
          "stage_executor.attn_blocks.0.query.weight",
          "stage_executor.attn_blocks.0.value.bias",
          "stage_executor.attn_blocks.0.value.weight",
          "stage_executor.attn_blocks.1.dense.bias",
          "stage_executor.attn_blocks.1.dense.weight",
          "stage_executor.attn_blocks.1.key.bias",
          "stage_executor.attn_blocks.1.key.weight",
          "stage_executor.attn_blocks.1.layer_norm.bias",
          "stage_executor.attn_blocks.1.layer_norm.weight",
          "stage_executor.attn_blocks.1.query.bias"
        ],
        "skipped_shape": 1,
        "skipped_missing": 0,
        "skipped_excluded": 0,
        "skipped_reasons": {
          "shape": 1
        },
        "missing_keys": 0,
        "unexpected_keys": 0,
        "source_checkpoint": "/workspace/FeaturedMoE/experiments/run/AI502_transfer/artifacts_group1_best/checkpoints/native/beauty/retail_rocket/retail_r10_h13_width_refine/seed_4/best.pth",
        "freeze_report": {
          "enabled": false,
          "frozen_tensors": 0,
          "frozen_parameters": 0,
          "trainable_parameters_after_freeze": null,
          "frozen_parameter_names_sample": []
        },
        "init_delta_from_target": {
          "checked_tensors": 294,
          "changed_tensors": 278,
          "unchanged_tensors": 16,
          "max_abs_delta": 0.9569181203842163,
          "total_abs_delta": 249828.3661725188
        },
        "trainable_loaded_tensors": 294,
        "optimizer_report": {
          "enabled": true,
          "loaded_lr_scale": 0.35,
          "base_lr": 0.000692007,
          "loaded_lr": 0.00024220245,
          "loaded_param_tensors": 294,
          "loaded_parameters": 2904713,
          "other_param_tensors": 1,
          "other_parameters": 14241040
        },
        "train_delta_from_init": {
          "checked_tensors": 294,
          "changed_tensors": 269,
          "unchanged_tensors": 25,
          "max_abs_delta": 0.47332262992858887,
          "total_abs_delta": 45027.239994412754
        }
      },
      "freeze_report": {
        "enabled": false,
        "frozen_tensors": 0,
        "frozen_parameters": 0,
        "trainable_parameters_after_freeze": null,
        "frozen_parameter_names_sample": []
      },
      "source_checkpoint": "/workspace/FeaturedMoE/experiments/run/AI502_transfer/artifacts_group1_best/checkpoints/native/beauty/retail_rocket/retail_r10_h13_width_refine/seed_4/best.pth",
      "baseline_native_result": "",
      "baseline_native_checkpoint": "/workspace/FeaturedMoE/experiments/run/AI502_transfer/artifacts_group1_best/checkpoints/native/retail_rocket/retail_rocket/retail_r10_h13_width_refine/seed_4/best.pth",
      "fmoe_arch": {
        "arch_layout_id": -1,
        "fmoe_v2_layout_id": 0,
        "fmoe_stage_execution_mode": "serial",
        "router_impl": "learned",
        "router_impl_by_stage": {},
        "rule_router_cfg": {
          "variant": "ratio_bins",
          "n_bins": 5,
          "feature_per_expert": 4,
          "custom_stage_feature_map": {},
          "expert_bias": {}
        },
        "stage_inter_layer_style": "attn",
        "moe_block_variant": "moe",
        "router_group_feature_mode": "none",
        "router_use_hidden": true,
        "router_use_feature": true,
        "router_feature_proj_dim": 0,
        "router_feature_proj_layers": 1,
        "router_feature_scale": 1.0,
        "router_hidden_scale": 1.0,
        "router_group_feature_scale": 1.0,
        "rule_agreement_lambda": 0.0,
        "group_coverage_lambda": 0.0,
        "lr_scheduler_type": "warmup_cosine",
        "lr_scheduler_warmup_ratio": 0.0,
        "lr_scheduler_min_lr_ratio": 0.1,
        "lr_scheduler_plateau_factor": 0.5,
        "lr_scheduler_plateau_patience": 3,
        "n_pre_layer": 0,
        "n_pre_macro": 0,
        "n_pre_mid": 0,
        "n_pre_micro": 0,
        "n_post_layer": 0,
        "n_total_attn_layers": 2,
        "num_layers": 2
      },
      "n_pre_layer": 0,
      "n_pre_macro": 0,
      "n_pre_mid": 0,
      "n_pre_micro": 0,
      "n_post_layer": 0,
      "n_total_attn_layers": 2,
      "num_layers": 2,
      "early_valid_main_eval_filter": {
        "total_targets": 21584,
        "seen_targets": 19289,
        "unseen_targets": 2295,
        "dropped_eval_rows": 2295,
        "enabled": true
      },
      "macro_1.entropy_mean": 2.414617572847942,
      "macro_1.n_eff": 11.93832596611173,
      "macro_1.cv_usage": 0.07187496842816567,
      "macro_1.dead_expert_frac": 0.0,
      "macro_1.top1_max_frac": 0.7548350612629595,
      "macro_1.route_jitter_adjacent": 0.0,
      "macro_1.route_jitter_session": 0.0,
      "macro_1.route_consistency_knn_js": 0.002556259065225798,
      "macro_1.route_consistency_knn_score": 0.9974470053827944,
      "macro_1.route_consistency_group_knn_js": 0.0016801188706114523,
      "macro_1.route_consistency_group_knn_score": 0.9983212917389904,
      "macro_1.route_consistency_intra_group_knn_mean_js": 0.0009394109668866011,
      "macro_1.route_consistency_intra_group_knn_mean_score": 0.9990612771286694,
      "macro_1.route_consistency_feature_group_knn_mean_js": 0.004946864031260768,
      "macro_1.route_consistency_feature_group_knn_mean_score": 0.9950657113860392,
      "macro_1.route_consistency_feature_group_knn_tempo_js": 0.005886876026376961,
      "macro_1.route_consistency_feature_group_knn_tempo_score": 0.9941304176763621,
      "macro_1.route_consistency_feature_group_knn_focus_js": 0.004362321235764194,
      "macro_1.route_consistency_feature_group_knn_focus_score": 0.9956471798668763,
      "macro_1.route_consistency_feature_group_knn_memory_js": 0.0038734737195466693,
      "macro_1.route_consistency_feature_group_knn_memory_score": 0.9961340185030172,
      "macro_1.route_consistency_feature_group_knn_exposure_js": 0.005664785143355249,
      "macro_1.route_consistency_feature_group_knn_exposure_score": 0.9943512294979012,
      "macro_1.condition_norm": 0.0,
      "macro_1.stage_delta_norm": 3.620706835068801,
      "macro_1.shared_delta_norm": 8.157515115363232,
      "macro_1.moe_delta_norm": 3.620706835068801,
      "macro_1.residual_delta_norm": 3.620706835068801,
      "macro_1.alpha_value": 1.0,
      "macro_1.alpha_effective": 1.0,
      "macro_1.expert_similarity_mean": 0.1987845003604889,
      "macro_1.expert_similarity_max": 0.4139466881752014,
      "macro_1.group_n_eff": 3.985370929044825,
      "macro_1.group_cv_usage": 0.060586176808435435,
      "macro_1.group_top1_max_frac": 0.7723279924599434,
      "macro_1.group_entropy_mean": 1.3378047562244737,
      "macro_1.factored_group_entropy_mean": 0.0
    }
  ],
  "run_group": "ai502_transfer_group1_best",
  "run_axis": "group1_best_hparam_transfer",
  "run_phase": "AI502_G1_T_beauty_to_retail_rocket_retail_r10_h13_width_refine_full_model_init_loaded_lr_0_35_s4",
  "parent_result": "",
  "interrupted": false,
  "interrupted_at": null,
  "time_budget_hours": 0.0,
  "time_budget_reached": false,
  "time_budget_reached_at_sec": null,
  "stop_reason": "",
  "tuned_search": {},
  "fixed_search": {
    "learning_rate": 0.000692007
  },
  "context_fixed": {
    "fmoe_v2_layout_id": 0,
    "fmoe_stage_execution_mode": "serial",
    "router_impl": "learned",
    "router_impl_by_stage": {},
    "rule_router": {
      "variant": "ratio_bins",
      "n_bins": 5,
      "feature_per_expert": 4,
      "custom_stage_feature_map": {},
      "expert_bias": {}
    },
    "router_use_hidden": true,
    "router_use_feature": true,
    "router_feature_proj_dim": 0,
    "router_feature_proj_layers": 1,
    "router_feature_scale": 1.0,
    "router_hidden_scale": 1.0,
    "router_group_feature_scale": 1.0,
    "rule_agreement_lambda": 0.0,
    "group_coverage_lambda": 0.0,
    "lr_scheduler_type": "warmup_cosine",
    "lr_scheduler_warmup_ratio": 0.0,
    "lr_scheduler_min_lr_ratio": 0.1,
    "lr_scheduler_plateau_factor": 0.5,
    "lr_scheduler_plateau_patience": 3,
    "num_layers": 2,
    "group_top_k": 0,
    "fmoe_v2_parallel_stage_gate_top_k": 0,
    "fmoe_v2_parallel_stage_gate_temperature": 1.0,
    "fmoe_v2_stage_merge_aux_enable": false,
    "fmoe_v2_stage_merge_aux_lambda_scale": 1.0,
    "fmoe_schedule_enable": false,
    "alpha_warmup_until": 0,
    "temperature_warmup_until": 0,
    "moe_top_k": 0,
    "moe_top_k_warmup_until": 0,
    "search_space_type_overrides": {
      "learning_rate": "choice"
    }
  },
  "best_params": {},
  "best_checkpoint_file": "/workspace/FeaturedMoE/experiments/run/AI502_transfer/artifacts_group1_best/checkpoints/transfer/beauty_to_retail_rocket/retail_r10_h13_width_refine/seed_4/full_model_init/loaded_lr_0.35/best.pth",
  "best_mrr@20": 0.3683,
  "best_hr@10": 0.5687,
  "test_mrr@20": 0.3659,
  "test_hr@10": 0.5565,
  "avg_epoch_time_sec": 53.91771895885468,
  "avg_epoch_per_hour": 66.76840321726532,
  "test_eval_time_sec": 2.0558948516845703,
  "test_eval_batches_per_sec": 5.350468187118986,
  "test_eval_targets_per_sec": 10204.802051432394,
  "best_valid_result": {
    "recall@10": 0.5687,
    "recall@20": 0.6457,
    "mrr@10": 0.363,
    "mrr@20": 0.3683,
    "ndcg@10": 0.4121,
    "ndcg@20": 0.4316,
    "hit@10": 0.5687,
    "hit@20": 0.6457,
    "precision@10": 0.0569,
    "precision@20": 0.0323
  },
  "test_result": {
    "recall@10": 0.5565,
    "recall@20": 0.6284,
    "mrr@10": 0.361,
    "mrr@20": 0.3659,
    "ndcg@10": 0.4078,
    "ndcg@20": 0.426,
    "hit@10": 0.5565,
    "hit@20": 0.6284,
    "precision@10": 0.0556,
    "precision@20": 0.0314
  },
  "best_valid_special_metrics": {
    "split": "best_valid",
    "overall": {
      "count": 21584,
      "hit@5": 0.4363417346182357,
      "hit@10": 0.5106097108969607,
      "hit@20": 0.5803836174944403,
      "ndcg@5": 0.3452089849080727,
      "ndcg@10": 0.36921892143382773,
      "ndcg@20": 0.3868804179129223,
      "mrr@5": 0.31490687604060186,
      "mrr@10": 0.32481140578462514,
      "mrr@20": 0.32967033250059924
    },
    "overall_seen_target": {
      "count": 19289,
      "hit@5": 0.4871170096946446,
      "hit@10": 0.5686660791124475,
      "hit@20": 0.6456529628285551,
      "ndcg@5": 0.38578821188511486,
      "ndcg@10": 0.41214818614311244,
      "ndcg@20": 0.4316361351269413,
      "mrr@5": 0.3520849540685197,
      "mrr@10": 0.3629566823443807,
      "mrr@20": 0.36831851956937217
    },
    "overall_unseen_target": {
      "count": 2295,
      "hit@5": 0.009586056644880174,
      "hit@10": 0.022657952069716776,
      "hit@20": 0.0318082788671024,
      "ndcg@5": 0.004148980916715136,
      "ndcg@10": 0.00840733669422291,
      "ndcg@20": 0.010717877894964613,
      "mrr@5": 0.002432825025130461,
      "mrr@10": 0.004208251291760172,
      "mrr@20": 0.004840319267674988
    },
    "slices": {
      "target_popularity_abs": {
        "cold_0": {
          "count": 2295,
          "hit@5": 0.009586056644880174,
          "hit@10": 0.022657952069716776,
          "hit@20": 0.0318082788671024,
          "ndcg@5": 0.004148980916715136,
          "ndcg@10": 0.00840733669422291,
          "ndcg@20": 0.010717877894964613,
          "mrr@5": 0.002432825025130461,
          "mrr@10": 0.004208251291760172,
          "mrr@20": 0.004840319267674988
        },
        "rare_1_5": {
          "count": 5000,
          "hit@5": 0.426,
          "hit@10": 0.4758,
          "hit@20": 0.525,
          "ndcg@5": 0.34470040459036827,
          "ndcg@10": 0.3608574197947979,
          "ndcg@20": 0.37326036876142027,
          "mrr@5": 0.317483333799243,
          "mrr@10": 0.3241804768174887,
          "mrr@20": 0.32756951040923593
        },
        "6_20": {
          "count": 6501,
          "hit@5": 0.4625442239655438,
          "hit@10": 0.5445316105214583,
          "hit@20": 0.6283648669435471,
          "ndcg@5": 0.3757654942745173,
          "ndcg@10": 0.40225029309847377,
          "ndcg@20": 0.42349191539481207,
          "mrr@5": 0.3469056048002303,
          "mrr@10": 0.3578216301693016,
          "mrr@20": 0.3636771211475982
        },
        "21_100": {
          "count": 6377,
          "hit@5": 0.5308138623177042,
          "hit@10": 0.6333699231613611,
          "hit@20": 0.7232240865610788,
          "ndcg@5": 0.4074067700258781,
          "ndcg@10": 0.4405320884760073,
          "ndcg@20": 0.4632627393466768,
          "mrr@5": 0.36652030817427117,
          "mrr@10": 0.3801666342022278,
          "mrr@20": 0.38641066587988215
        },
        "101+": {
          "count": 1411,
          "hit@5": 0.6194188518781006,
          "hit@10": 0.7165131112686038,
          "hit@20": 0.8022678951098512,
          "ndcg@5": 0.47985991875724876,
          "ndcg@10": 0.5112239403939264,
          "ndcg@20": 0.5330830162020121,
          "mrr@5": 0.4333215223230596,
          "mrr@10": 0.44624239377397584,
          "mrr@20": 0.45233351596803384
        }
      },
      "target_popularity_abs_legacy": {
        "<=5": {
          "count": 7295,
          "hit@5": 0.2949965729952022,
          "hit@10": 0.33324194653872513,
          "hit@20": 0.3698423577793009,
          "ndcg@5": 0.23756325348261859,
          "ndcg@10": 0.24997696184883222,
          "ndcg@20": 0.25920484901659285,
          "mrr@5": 0.21836874604919662,
          "mrr@10": 0.22351752170007305,
          "mrr@20": 0.22603921655455708
        },
        "6-20": {
          "count": 6501,
          "hit@5": 0.4625442239655438,
          "hit@10": 0.5445316105214583,
          "hit@20": 0.6283648669435471,
          "ndcg@5": 0.3757654942745173,
          "ndcg@10": 0.40225029309847377,
          "ndcg@20": 0.42349191539481207,
          "mrr@5": 0.3469056048002303,
          "mrr@10": 0.3578216301693016,
          "mrr@20": 0.3636771211475982
        },
        "21-100": {
          "count": 6377,
          "hit@5": 0.5308138623177042,
          "hit@10": 0.6333699231613611,
          "hit@20": 0.7232240865610788,
          "ndcg@5": 0.4074067700258781,
          "ndcg@10": 0.4405320884760073,
          "ndcg@20": 0.4632627393466768,
          "mrr@5": 0.36652030817427117,
          "mrr@10": 0.3801666342022278,
          "mrr@20": 0.38641066587988215
        },
        ">100": {
          "count": 1411,
          "hit@5": 0.6194188518781006,
          "hit@10": 0.7165131112686038,
          "hit@20": 0.8022678951098512,
          "ndcg@5": 0.47985991875724876,
          "ndcg@10": 0.5112239403939264,
          "ndcg@20": 0.5330830162020121,
          "mrr@5": 0.4333215223230596,
          "mrr@10": 0.44624239377397584,
          "mrr@20": 0.45233351596803384
        }
      },
      "session_len": {
        "<=7": {
          "count": 19650,
          "hit@5": 0.449618320610687,
          "hit@10": 0.5236132315521629,
          "hit@20": 0.5926208651399492,
          "ndcg@5": 0.3568995051211073,
          "ndcg@10": 0.3808342918655041,
          "ndcg@20": 0.3983169384319667,
          "mrr@5": 0.32605173935037834,
          "mrr@10": 0.3359326717648039,
          "mrr@20": 0.3407500366159447
        },
        "8-12": {
          "count": 1250,
          "hit@5": 0.3368,
          "hit@10": 0.4128,
          "hit@20": 0.4992,
          "ndcg@5": 0.2524712161064148,
          "ndcg@10": 0.277042129611969,
          "ndcg@20": 0.29873637133836745,
          "mrr@5": 0.2245866672039032,
          "mrr@10": 0.23472603250741958,
          "mrr@20": 0.24060416161715983
        },
        "13+": {
          "count": 684,
          "hit@5": 0.23684210526315788,
          "hit@10": 0.3157894736842105,
          "hit@20": 0.37719298245614036,
          "ndcg@5": 0.17883981651032876,
          "ndcg@10": 0.20398348399944471,
          "ndcg@20": 0.21941321033831926,
          "mrr@5": 0.1597953219598497,
          "mrr@10": 0.16994859889280378,
          "mrr@20": 0.17413894030434346
        }
      },
      "session_len_legacy": {
        "1-2": {
          "count": 10703,
          "hit@5": 0.46874708025787165,
          "hit@10": 0.5338690086891525,
          "hit@20": 0.5974025974025974,
          "ndcg@5": 0.38125077203524554,
          "ndcg@10": 0.40235779956324264,
          "ndcg@20": 0.41848733474871247,
          "mrr@5": 0.35207729973542873,
          "mrr@10": 0.3608140952896985,
          "mrr@20": 0.36527796896313947
        },
        "3-5": {
          "count": 7537,
          "hit@5": 0.4396974923709699,
          "hit@10": 0.5247445933395251,
          "hit@20": 0.6001061430277299,
          "ndcg@5": 0.33889698817746716,
          "ndcg@10": 0.36636140650758314,
          "ndcg@20": 0.3854168841942277,
          "mrr@5": 0.3054553100351663,
          "mrr@10": 0.3167691777581496,
          "mrr@20": 0.32199899189463815
        },
        "6-10": {
          "count": 2339,
          "hit@5": 0.3552800342026507,
          "hit@10": 0.43693886276186406,
          "hit@20": 0.5160324925181702,
          "ndcg@5": 0.2668390732104068,
          "ndcg@10": 0.2932915508798067,
          "ndcg@20": 0.31323981161502856,
          "mrr@5": 0.23749465637734019,
          "mrr@10": 0.24843780827629305,
          "mrr@20": 0.2538857297759221
        },
        "11+": {
          "count": 1005,
          "hit@5": 0.25472636815920396,
          "hit@10": 0.3283582089552239,
          "hit@20": 0.4009950248756219,
          "ndcg@5": 0.19110500002974895,
          "ndcg@10": 0.2144386200465966,
          "ndcg@20": 0.2326388267438803,
          "mrr@5": 0.17009950287603026,
          "mrr@10": 0.1794535266152069,
          "mrr@20": 0.18436739405441047
        }
      }
    },
    "counts": {
      "target_popularity_abs": {
        "cold_0": 2295,
        "rare_1_5": 5000,
        "6_20": 6501,
        "21_100": 6377,
        "101+": 1411
      },
      "target_popularity_abs_legacy": {
        "<=5": 7295,
        "6-20": 6501,
        "21-100": 6377,
        ">100": 1411
      },
      "session_len": {
        "<=7": 19650,
        "8-12": 1250,
        "13+": 684
      },
      "session_len_legacy": {
        "1-2": 10703,
        "3-5": 7537,
        "6-10": 2339,
        "11+": 1005
      }
    },
    "config_snapshot": {
      "target_popularity_abs_bins": [
        "cold_0",
        "rare_1_5",
        "6_20",
        "21_100",
        "101+"
      ],
      "target_popularity_abs_bins_legacy": [
        "<=5",
        "6-20",
        "21-100",
        ">100"
      ],
      "session_len_bins": [
        "<=7",
        "8-12",
        "13+"
      ],
      "session_len_bins_legacy": [
        "1-2",
        "3-5",
        "6-10",
        "11+"
      ],
      "item_count_source": "train_split",
      "item_count_definition": "train_interaction_count_per_item",
      "new_user_enabled": false,
      "feature_logging_available": true,
      "split": "best_valid",
      "item_seq_len_field": "item_length",
      "new_user_field": ""
    }
  },
  "early_valid_result": {
    "recall@10": 0.3603,
    "recall@20": 0.4076,
    "mrr@10": 0.2347,
    "mrr@20": 0.238,
    "ndcg@10": 0.2648,
    "ndcg@20": 0.2767,
    "hit@10": 0.3603,
    "hit@20": 0.4076,
    "precision@10": 0.036,
    "precision@20": 0.0204
  },
  "early_valid_special_metrics": {
    "split": "early_valid",
    "overall": {
      "count": 21584,
      "hit@5": 0.2812731653076353,
      "hit@10": 0.32524091919940695,
      "hit@20": 0.367772424017791,
      "ndcg@5": 0.22541581675564915,
      "ndcg@10": 0.23963816812727254,
      "ndcg@20": 0.25035169760346565,
      "mrr@5": 0.20682063908367973,
      "mrr@10": 0.21269284246911918,
      "mrr@20": 0.2156128697665139
    },
    "overall_seen_target": {
      "count": 19289,
      "hit@5": 0.31116180206335214,
      "hit@10": 0.36025714137591375,
      "hit@20": 0.40758981803100214,
      "ndcg@5": 0.24888976894219017,
      "ndcg@10": 0.26477202483089723,
      "ndcg@20": 0.27669548628888174,
      "mrr@5": 0.2281559441802389,
      "mrr@10": 0.23471423028737726,
      "mrr@20": 0.23796422389803837
    },
    "overall_unseen_target": {
      "count": 2295,
      "hit@5": 0.030065359477124184,
      "hit@10": 0.03093681917211329,
      "hit@20": 0.033115468409586055,
      "ndcg@5": 0.02812210707103505,
      "ndcg@10": 0.028393304529792603,
      "ndcg@20": 0.02893760612068093,
      "mrr@5": 0.027501815550986977,
      "mrr@10": 0.027607635660239035,
      "mrr@20": 0.02775436438831109
    },
    "slices": {
      "target_popularity_abs": {
        "cold_0": {
          "count": 2295,
          "hit@5": 0.030065359477124184,
          "hit@10": 0.03093681917211329,
          "hit@20": 0.033115468409586055,
          "ndcg@5": 0.02812210707103505,
          "ndcg@10": 0.028393304529792603,
          "ndcg@20": 0.02893760612068093,
          "mrr@5": 0.027501815550986977,
          "mrr@10": 0.027607635660239035,
          "mrr@20": 0.02775436438831109
        },
        "rare_1_5": {
          "count": 5000,
          "hit@5": 0.2058,
          "hit@10": 0.224,
          "hit@20": 0.2418,
          "ndcg@5": 0.1819169170677662,
          "ndcg@10": 0.18780344638228416,
          "ndcg@20": 0.1923339604318142,
          "mrr@5": 0.17400000015199185,
          "mrr@10": 0.17642857163399459,
          "mrr@20": 0.17768898214772344
        },
        "6_20": {
          "count": 6501,
          "hit@5": 0.21442854945393017,
          "hit@10": 0.25457621904322414,
          "hit@20": 0.29149361636671284,
          "ndcg@5": 0.16964966937076714,
          "ndcg@10": 0.18266960526957657,
          "ndcg@20": 0.1919693931893667,
          "mrr@5": 0.15475824256618836,
          "mrr@10": 0.16015448210248945,
          "mrr@20": 0.16268953606841602
        },
        "21_100": {
          "count": 6377,
          "hit@5": 0.4011290575505724,
          "hit@10": 0.4745177983377764,
          "hit@20": 0.5533950133291516,
          "ndcg@5": 0.30926504661544507,
          "ndcg@10": 0.3330037718901949,
          "ndcg@20": 0.35282268853131105,
          "mrr@5": 0.27872824271644603,
          "mrr@10": 0.2885292141937959,
          "mrr@20": 0.29390353650282275
        },
        "101+": {
          "count": 1411,
          "hit@5": 0.7236002834868888,
          "hit@10": 0.813607370659107,
          "hit@20": 0.8710134656272147,
          "ndcg@5": 0.5784368993203578,
          "ndcg@10": 0.6074204095325767,
          "ndcg@20": 0.6219462246484236,
          "mrr@5": 0.5296716284954658,
          "mrr@10": 0.5415626100504086,
          "mrr@20": 0.5455559729067126
        }
      },
      "target_popularity_abs_legacy": {
        "<=5": {
          "count": 7295,
          "hit@5": 0.150514050719671,
          "hit@10": 0.16326250856751198,
          "hit@20": 0.17614804660726524,
          "ndcg@5": 0.13353321741834906,
          "ndcg@10": 0.1376531687193002,
          "ndcg@20": 0.14092962415435692,
          "mrr@5": 0.12791181185051054,
          "mrr@10": 0.12960964797946833,
          "mrr@20": 0.13051969527207555
        },
        "6-20": {
          "count": 6501,
          "hit@5": 0.21442854945393017,
          "hit@10": 0.25457621904322414,
          "hit@20": 0.29149361636671284,
          "ndcg@5": 0.16964966937076714,
          "ndcg@10": 0.18266960526957657,
          "ndcg@20": 0.1919693931893667,
          "mrr@5": 0.15475824256618836,
          "mrr@10": 0.16015448210248945,
          "mrr@20": 0.16268953606841602
        },
        "21-100": {
          "count": 6377,
          "hit@5": 0.4011290575505724,
          "hit@10": 0.4745177983377764,
          "hit@20": 0.5533950133291516,
          "ndcg@5": 0.30926504661544507,
          "ndcg@10": 0.3330037718901949,
          "ndcg@20": 0.35282268853131105,
          "mrr@5": 0.27872824271644603,
          "mrr@10": 0.2885292141937959,
          "mrr@20": 0.29390353650282275
        },
        ">100": {
          "count": 1411,
          "hit@5": 0.7236002834868888,
          "hit@10": 0.813607370659107,
          "hit@20": 0.8710134656272147,
          "ndcg@5": 0.5784368993203578,
          "ndcg@10": 0.6074204095325767,
          "ndcg@20": 0.6219462246484236,
          "mrr@5": 0.5296716284954658,
          "mrr@10": 0.5415626100504086,
          "mrr@20": 0.5455559729067126
        }
      },
      "session_len": {
        "<=7": {
          "count": 19650,
          "hit@5": 0.29002544529262086,
          "hit@10": 0.33440203562340964,
          "hit@20": 0.37735368956743004,
          "ndcg@5": 0.23348433584202338,
          "ndcg@10": 0.24785757559249721,
          "ndcg@20": 0.258690231180828,
          "mrr@5": 0.21466072976968367,
          "mrr@10": 0.2206061436990442,
          "mrr@20": 0.22356560142838772
        },
        "8-12": {
          "count": 1250,
          "hit@5": 0.2096,
          "hit@10": 0.252,
          "hit@20": 0.2944,
          "ndcg@5": 0.15939256064891816,
          "ndcg@10": 0.1728081854581833,
          "ndcg@20": 0.18329076573848724,
          "mrr@5": 0.1425600003361702,
          "mrr@10": 0.14792666710019112,
          "mrr@20": 0.1506771802276373
        },
        "13+": {
          "count": 684,
          "hit@5": 0.1608187134502924,
          "hit@10": 0.195906432748538,
          "hit@20": 0.22660818713450293,
          "ndcg@5": 0.11427936951319377,
          "ndcg@10": 0.12564126994700459,
          "ndcg@20": 0.13335459239301625,
          "mrr@5": 0.09902534150240715,
          "mrr@10": 0.10371820802925623,
          "mrr@20": 0.1058152597778809
        }
      },
      "session_len_legacy": {
        "1-2": {
          "count": 10703,
          "hit@5": 0.30935251798561153,
          "hit@10": 0.3494347379239466,
          "hit@20": 0.3882089133887695,
          "ndcg@5": 0.2536971693806121,
          "ndcg@10": 0.26672333310466384,
          "ndcg@20": 0.27654648497373513,
          "mrr@5": 0.23513189481929297,
          "mrr@10": 0.24054652428452705,
          "mrr@20": 0.24325319325305486
        },
        "3-5": {
          "count": 7537,
          "hit@5": 0.2739816903277166,
          "hit@10": 0.3261244527000133,
          "hit@20": 0.3724293485471673,
          "ndcg@5": 0.21446123969512196,
          "ndcg@10": 0.23126130296947692,
          "ndcg@20": 0.24290662846546898,
          "mrr@5": 0.19470611684784517,
          "mrr@10": 0.20160299189427305,
          "mrr@20": 0.20476724814311711
        },
        "6-10": {
          "count": 2339,
          "hit@5": 0.22488242838820008,
          "hit@10": 0.26336041043180847,
          "hit@20": 0.31338178708849934,
          "ndcg@5": 0.1760529211414528,
          "ndcg@10": 0.18839428671000605,
          "ndcg@20": 0.20083726382551156,
          "mrr@5": 0.1596907513067222,
          "mrr@10": 0.1647237664763109,
          "mrr@20": 0.16803104841349828
        },
        "11+": {
          "count": 1005,
          "hit@5": 0.1681592039800995,
          "hit@10": 0.20497512437810944,
          "hit@20": 0.2417910447761194,
          "ndcg@5": 0.12126571028979856,
          "ndcg@10": 0.13327334283003167,
          "ndcg@20": 0.14245611300219352,
          "mrr@5": 0.1058540634254911,
          "mrr@10": 0.11086788332432657,
          "mrr@20": 0.11332724592949621
        }
      }
    },
    "counts": {
      "target_popularity_abs": {
        "cold_0": 2295,
        "rare_1_5": 5000,
        "6_20": 6501,
        "21_100": 6377,
        "101+": 1411
      },
      "target_popularity_abs_legacy": {
        "<=5": 7295,
        "6-20": 6501,
        "21-100": 6377,
        ">100": 1411
      },
      "session_len": {
        "<=7": 19650,
        "8-12": 1250,
        "13+": 684
      },
      "session_len_legacy": {
        "1-2": 10703,
        "3-5": 7537,
        "6-10": 2339,
        "11+": 1005
      }
    },
    "config_snapshot": {
      "target_popularity_abs_bins": [
        "cold_0",
        "rare_1_5",
        "6_20",
        "21_100",
        "101+"
      ],
      "target_popularity_abs_bins_legacy": [
        "<=5",
        "6-20",
        "21-100",
        ">100"
      ],
      "session_len_bins": [
        "<=7",
        "8-12",
        "13+"
      ],
      "session_len_bins_legacy": [
        "1-2",
        "3-5",
        "6-10",
        "11+"
      ],
      "item_count_source": "train_split",
      "item_count_definition": "train_interaction_count_per_item",
      "new_user_enabled": false,
      "feature_logging_available": true,
      "split": "early_valid",
      "item_seq_len_field": "item_length",
      "new_user_field": ""
    }
  },
  "test_special_metrics": {
    "split": "test",
    "overall": {
      "count": 20980,
      "hit@5": 0.4043374642516683,
      "hit@10": 0.47087702573879886,
      "hit@20": 0.532697807435653,
      "ndcg@5": 0.3226998354390874,
      "ndcg@10": 0.34434590231559753,
      "ndcg@20": 0.35997713027722616,
      "mrr@5": 0.2955115988381825,
      "mrr@10": 0.3045213702625752,
      "mrr@20": 0.3088110236912696
    },
    "overall_seen_target": {
      "count": 17672,
      "hit@5": 0.4785536441828882,
      "hit@10": 0.5564735174287008,
      "hit@20": 0.6283952014486193,
      "ndcg@5": 0.38242048265108053,
      "ndcg@10": 0.40777506126995644,
      "ndcg@20": 0.42596289298790996,
      "mrr@5": 0.35039516430198064,
      "mrr@10": 0.3609521751940898,
      "mrr@20": 0.36594486638655715
    },
    "overall_unseen_target": {
      "count": 3308,
      "hit@5": 0.007859733978234583,
      "hit@10": 0.013603385731559855,
      "hit@20": 0.021463119709794438,
      "ndcg@5": 0.003660150575017987,
      "ndcg@10": 0.005494603330884332,
      "ndcg@20": 0.007467940850622565,
      "mrr@5": 0.0023125755986899248,
      "mrr@10": 0.0030566832161043403,
      "mrr@20": 0.0035905677931070182
    },
    "slices": {
      "target_popularity_abs": {
        "cold_0": {
          "count": 3308,
          "hit@5": 0.007859733978234583,
          "hit@10": 0.013603385731559855,
          "hit@20": 0.021463119709794438,
          "ndcg@5": 0.003660150575017987,
          "ndcg@10": 0.005494603330884332,
          "ndcg@20": 0.007467940850622565,
          "mrr@5": 0.0023125755986899248,
          "mrr@10": 0.0030566832161043403,
          "mrr@20": 0.0035905677931070182
        },
        "rare_1_5": {
          "count": 4991,
          "hit@5": 0.40853536365457827,
          "hit@10": 0.46764175515928674,
          "hit@20": 0.5129232618713685,
          "ndcg@5": 0.3335027328368252,
          "ndcg@10": 0.3527056180960285,
          "ndcg@20": 0.3641531488187708,
          "mrr@5": 0.308351700180185,
          "mrr@10": 0.3163290755202622,
          "mrr@20": 0.3194695987371626
        },
        "6_20": {
          "count": 5931,
          "hit@5": 0.458607317484404,
          "hit@10": 0.5363345135727533,
          "hit@20": 0.6172652166582364,
          "ndcg@5": 0.36985587054190555,
          "ndcg@10": 0.39517613905233107,
          "ndcg@20": 0.41571720066078194,
          "mrr@5": 0.3404007199024234,
          "mrr@10": 0.3509591794691325,
          "mrr@20": 0.3566363665743685
        },
        "21_100": {
          "count": 5570,
          "hit@5": 0.5262118491921005,
          "hit@10": 0.6204667863554758,
          "hit@20": 0.7070017953321365,
          "ndcg@5": 0.4128956035341352,
          "ndcg@10": 0.4435059736350708,
          "ndcg@20": 0.4653418375142387,
          "mrr@5": 0.3752274094326706,
          "mrr@10": 0.3879400710991619,
          "mrr@20": 0.39390960519655177
        },
        "101+": {
          "count": 1180,
          "hit@5": 0.65,
          "hit@10": 0.7313559322033898,
          "hit@20": 0.8016949152542373,
          "ndcg@5": 0.5086262287729878,
          "ndcg@10": 0.5353637194734508,
          "ndcg@20": 0.5530128195376719,
          "mrr@5": 0.46124293869834837,
          "mrr@10": 0.47252824970726237,
          "mrr@20": 0.4773034918548192
        }
      },
      "target_popularity_abs_legacy": {
        "<=5": {
          "count": 8299,
          "hit@5": 0.2488251596577901,
          "hit@10": 0.2866610434992168,
          "hit@20": 0.317026147728642,
          "ndcg@5": 0.20202674029289722,
          "ndcg@10": 0.214306529429551,
          "ndcg@20": 0.22197762550769304,
          "mrr@5": 0.18636381921674533,
          "mrr@10": 0.19145799783112444,
          "mrr@20": 0.19355950904407476
        },
        "6-20": {
          "count": 5931,
          "hit@5": 0.458607317484404,
          "hit@10": 0.5363345135727533,
          "hit@20": 0.6172652166582364,
          "ndcg@5": 0.36985587054190555,
          "ndcg@10": 0.39517613905233107,
          "ndcg@20": 0.41571720066078194,
          "mrr@5": 0.3404007199024234,
          "mrr@10": 0.3509591794691325,
          "mrr@20": 0.3566363665743685
        },
        "21-100": {
          "count": 5570,
          "hit@5": 0.5262118491921005,
          "hit@10": 0.6204667863554758,
          "hit@20": 0.7070017953321365,
          "ndcg@5": 0.4128956035341352,
          "ndcg@10": 0.4435059736350708,
          "ndcg@20": 0.4653418375142387,
          "mrr@5": 0.3752274094326706,
          "mrr@10": 0.3879400710991619,
          "mrr@20": 0.39390960519655177
        },
        ">100": {
          "count": 1180,
          "hit@5": 0.65,
          "hit@10": 0.7313559322033898,
          "hit@20": 0.8016949152542373,
          "ndcg@5": 0.5086262287729878,
          "ndcg@10": 0.5353637194734508,
          "ndcg@20": 0.5530128195376719,
          "mrr@5": 0.46124293869834837,
          "mrr@10": 0.47252824970726237,
          "mrr@20": 0.4773034918548192
        }
      },
      "session_len": {
        "<=7": {
          "count": 19301,
          "hit@5": 0.4156779441479716,
          "hit@10": 0.4824102378115124,
          "hit@20": 0.5437542096264443,
          "ndcg@5": 0.3327860304092065,
          "ndcg@10": 0.35448412936182566,
          "ndcg@20": 0.36999233634022505,
          "mrr@5": 0.3051689900208876,
          "mrr@10": 0.3141946760481778,
          "mrr@20": 0.31844897619836793
        },
        "8-12": {
          "count": 1044,
          "hit@5": 0.28735632183908044,
          "hit@10": 0.3611111111111111,
          "hit@20": 0.43582375478927204,
          "ndcg@5": 0.21573748687903085,
          "ndcg@10": 0.23996438594156755,
          "ndcg@20": 0.25886491549083557,
          "mrr@5": 0.19209770150339922,
          "mrr@10": 0.20230911391648068,
          "mrr@20": 0.2075026143534944
        },
        "13+": {
          "count": 635,
          "hit@5": 0.25196850393700787,
          "hit@10": 0.30078740157480316,
          "hit@20": 0.35590551181102364,
          "ndcg@5": 0.19198336737362418,
          "ndcg@10": 0.20780477298526312,
          "ndcg@20": 0.22180021691510057,
          "mrr@5": 0.17199475096435998,
          "mrr@10": 0.17854518232148464,
          "mrr@20": 0.1824233985088003
        }
      },
      "session_len_legacy": {
        "1-2": {
          "count": 11029,
          "hit@5": 0.42696527337020584,
          "hit@10": 0.48608214706682384,
          "hit@20": 0.541118868437755,
          "ndcg@5": 0.35141783941093646,
          "ndcg@10": 0.37064142548840134,
          "ndcg@20": 0.38453319142925974,
          "mrr@5": 0.32619306721689695,
          "mrr@10": 0.33418959028115675,
          "mrr@20": 0.3379871986228127
        },
        "3-5": {
          "count": 7067,
          "hit@5": 0.41304655440781096,
          "hit@10": 0.4912975803028159,
          "hit@20": 0.5597849158058582,
          "ndcg@5": 0.31764205919982724,
          "ndcg@10": 0.34309448876795207,
          "ndcg@20": 0.3604153187575697,
          "mrr@5": 0.28588745872396143,
          "mrr@10": 0.2964816357931474,
          "mrr@20": 0.3012391249171507
        },
        "6-10": {
          "count": 1984,
          "hit@5": 0.31350806451612906,
          "hit@10": 0.3845766129032258,
          "hit@20": 0.4596774193548387,
          "ndcg@5": 0.23817572099787573,
          "ndcg@10": 0.26138445619313466,
          "ndcg@20": 0.2804972731973976,
          "mrr@5": 0.21337365636962555,
          "mrr@10": 0.2230816779417857,
          "mrr@20": 0.22839302138140005
        },
        "11+": {
          "count": 900,
          "hit@5": 0.2588888888888889,
          "hit@10": 0.31444444444444447,
          "hit@20": 0.37777777777777777,
          "ndcg@5": 0.19682014869319067,
          "ndcg@10": 0.2148191507326232,
          "ndcg@20": 0.2308244191772408,
          "mrr@5": 0.17616666694482166,
          "mrr@10": 0.1836128752347496,
          "mrr@20": 0.18800645913514827
        }
      }
    },
    "counts": {
      "target_popularity_abs": {
        "cold_0": 3308,
        "rare_1_5": 4991,
        "6_20": 5931,
        "21_100": 5570,
        "101+": 1180
      },
      "target_popularity_abs_legacy": {
        "<=5": 8299,
        "6-20": 5931,
        "21-100": 5570,
        ">100": 1180
      },
      "session_len": {
        "<=7": 19301,
        "8-12": 1044,
        "13+": 635
      },
      "session_len_legacy": {
        "1-2": 11029,
        "3-5": 7067,
        "6-10": 1984,
        "11+": 900
      }
    },
    "config_snapshot": {
      "target_popularity_abs_bins": [
        "cold_0",
        "rare_1_5",
        "6_20",
        "21_100",
        "101+"
      ],
      "target_popularity_abs_bins_legacy": [
        "<=5",
        "6-20",
        "21-100",
        ">100"
      ],
      "session_len_bins": [
        "<=7",
        "8-12",
        "13+"
      ],
      "session_len_bins_legacy": [
        "1-2",
        "3-5",
        "6-10",
        "11+"
      ],
      "item_count_source": "train_split",
      "item_count_definition": "train_interaction_count_per_item",
      "new_user_enabled": false,
      "feature_logging_available": true,
      "split": "test",
      "item_seq_len_field": "item_length",
      "new_user_field": ""
    }
  },
  "best_valid_main_eval_filter": {
    "total_targets": 21584,
    "seen_targets": 19289,
    "unseen_targets": 2295,
    "dropped_eval_rows": 2295,
    "enabled": true
  },
  "test_main_eval_filter": {
    "total_targets": 20980,
    "seen_targets": 17672,
    "unseen_targets": 3308,
    "dropped_eval_rows": 3308,
    "enabled": true
  },
  "best_valid_cold_target_metrics": {
    "count": 2295,
    "hit@5": 0.009586056644880174,
    "hit@10": 0.022657952069716776,
    "hit@20": 0.0318082788671024,
    "ndcg@5": 0.004148980916715136,
    "ndcg@10": 0.00840733669422291,
    "ndcg@20": 0.010717877894964613,
    "mrr@5": 0.002432825025130461,
    "mrr@10": 0.004208251291760172,
    "mrr@20": 0.004840319267674988
  },
  "test_cold_target_metrics": {
    "count": 3308,
    "hit@5": 0.007859733978234583,
    "hit@10": 0.013603385731559855,
    "hit@20": 0.021463119709794438,
    "ndcg@5": 0.003660150575017987,
    "ndcg@10": 0.005494603330884332,
    "ndcg@20": 0.007467940850622565,
    "mrr@5": 0.0023125755986899248,
    "mrr@10": 0.0030566832161043403,
    "mrr@20": 0.0035905677931070182
  },
  "transfer_report": {
    "enabled": true,
    "mode": "full_model",
    "requested_mode": "full_model",
    "loaded_tensors": 294,
    "loaded_tensor_names_sample": [
      "input_ln.bias",
      "input_ln.weight",
      "position_embedding.weight",
      "stage_executor.attn_blocks.0.dense.bias",
      "stage_executor.attn_blocks.0.dense.weight",
      "stage_executor.attn_blocks.0.key.bias",
      "stage_executor.attn_blocks.0.key.weight",
      "stage_executor.attn_blocks.0.layer_norm.bias",
      "stage_executor.attn_blocks.0.layer_norm.weight",
      "stage_executor.attn_blocks.0.query.bias",
      "stage_executor.attn_blocks.0.query.weight",
      "stage_executor.attn_blocks.0.value.bias",
      "stage_executor.attn_blocks.0.value.weight",
      "stage_executor.attn_blocks.1.dense.bias",
      "stage_executor.attn_blocks.1.dense.weight",
      "stage_executor.attn_blocks.1.key.bias",
      "stage_executor.attn_blocks.1.key.weight",
      "stage_executor.attn_blocks.1.layer_norm.bias",
      "stage_executor.attn_blocks.1.layer_norm.weight",
      "stage_executor.attn_blocks.1.query.bias"
    ],
    "skipped_shape": 1,
    "skipped_missing": 0,
    "skipped_excluded": 0,
    "skipped_reasons": {
      "shape": 1
    },
    "missing_keys": 0,
    "unexpected_keys": 0,
    "source_checkpoint": "/workspace/FeaturedMoE/experiments/run/AI502_transfer/artifacts_group1_best/checkpoints/native/beauty/retail_rocket/retail_r10_h13_width_refine/seed_4/best.pth",
    "freeze_report": {
      "enabled": false,
      "frozen_tensors": 0,
      "frozen_parameters": 0,
      "trainable_parameters_after_freeze": null,
      "frozen_parameter_names_sample": []
    },
    "init_delta_from_target": {
      "checked_tensors": 294,
      "changed_tensors": 278,
      "unchanged_tensors": 16,
      "max_abs_delta": 0.9569181203842163,
      "total_abs_delta": 249828.3661725188
    },
    "trainable_loaded_tensors": 294,
    "optimizer_report": {
      "enabled": true,
      "loaded_lr_scale": 0.35,
      "base_lr": 0.000692007,
      "loaded_lr": 0.00024220245,
      "loaded_param_tensors": 294,
      "loaded_parameters": 2904713,
      "other_param_tensors": 1,
      "other_parameters": 14241040
    },
    "train_delta_from_init": {
      "checked_tensors": 294,
      "changed_tensors": 269,
      "unchanged_tensors": 25,
      "max_abs_delta": 0.47332262992858887,
      "total_abs_delta": 45027.239994412754
    }
  },
  "freeze_report": {
    "enabled": false,
    "frozen_tensors": 0,
    "frozen_parameters": 0,
    "trainable_parameters_after_freeze": null,
    "frozen_parameter_names_sample": []
  },
  "source_checkpoint": "/workspace/FeaturedMoE/experiments/run/AI502_transfer/artifacts_group1_best/checkpoints/native/beauty/retail_rocket/retail_r10_h13_width_refine/seed_4/best.pth",
  "baseline_native_result": "",
  "baseline_native_checkpoint": "/workspace/FeaturedMoE/experiments/run/AI502_transfer/artifacts_group1_best/checkpoints/native/retail_rocket/retail_rocket/retail_r10_h13_width_refine/seed_4/best.pth",
  "normal_result_mirror_file": "/workspace/FeaturedMoE/experiments/run/AI502_transfer/artifacts_group1_best/hyperopt_results/ai502_transfer_group1_best/normal/group1_best_hparam_transfer/AI502/retail_rocket/FMoEN3/retail_rocket_FeaturedMoE_N3_ai502_g1_t_beauty_to_retail_rocket_retail_r10_h13_width_refine_full_model_init_l_20260507_175822_112572_pid619084.json",
  "special_result_file": "/workspace/FeaturedMoE/experiments/run/AI502_transfer/artifacts_group1_best/hyperopt_results/ai502_transfer_group1_best/special/group1_best_hparam_transfer/AI502/retail_rocket/FMoEN3/retail_rocket_FeaturedMoE_N3_ai502_g1_t_beauty_to_retail_rocket_retail_r10_h13_width_refine_full_model_init_l_20260507_175822_112572_pid619084_special_metrics.json",
  "special_log_file": "/workspace/FeaturedMoE/experiments/run/artifacts/logs/ai502_transfer_group1_best/special/group1_best_hparam_transfer/AI502/retail_rocket/FMoEN3/retail_rocket_FeaturedMoE_N3_ai502_g1_t_beauty_to_retail_rocket_retail_r10_h13_width_refine_full_model_init_l_20260507_175822_112572_pid619084_special_metrics.json",
  "diag_dir": "/workspace/FeaturedMoE/experiments/run/AI502_transfer/artifacts_group1_best/hyperopt_results/ai502_transfer_group1_best/diag",
  "diag_meta_file": "/workspace/FeaturedMoE/experiments/run/AI502_transfer/artifacts_group1_best/hyperopt_results/ai502_transfer_group1_best/diag/meta.json",
  "diag_tier_a_final_file": "/workspace/FeaturedMoE/experiments/run/AI502_transfer/artifacts_group1_best/hyperopt_results/ai502_transfer_group1_best/diag/tier_a_final/final_metrics.csv",
  "diag_tier_b_internal_file": "/workspace/FeaturedMoE/experiments/run/AI502_transfer/artifacts_group1_best/hyperopt_results/ai502_transfer_group1_best/diag/tier_b_internal/internal_metrics.csv",
  "diag_viz_manifest_file": "/workspace/FeaturedMoE/experiments/run/AI502_transfer/artifacts_group1_best/hyperopt_results/ai502_transfer_group1_best/diag/tier_c_viz/viz_manifest.json",
  "diag_viz_feature_pca_file": "/workspace/FeaturedMoE/experiments/run/AI502_transfer/artifacts_group1_best/hyperopt_results/ai502_transfer_group1_best/diag/tier_c_viz/viz_feature_pca.csv.gz",
  "diag_viz_router_input_pca_file": "/workspace/FeaturedMoE/experiments/run/AI502_transfer/artifacts_group1_best/hyperopt_results/ai502_transfer_group1_best/diag/tier_c_viz/viz_router_input_pca.csv.gz",
  "diag_viz_group_feature_pca_file": "/workspace/FeaturedMoE/experiments/run/AI502_transfer/artifacts_group1_best/hyperopt_results/ai502_transfer_group1_best/diag/tier_c_viz/viz_group_feature_pca.csv.gz",
  "diag_raw_trial_summary_file": "/workspace/FeaturedMoE/experiments/run/AI502_transfer/artifacts_group1_best/hyperopt_results/ai502_transfer_group1_best/diag/raw/trial_summary.csv",
  "diag_raw_best_valid_file": "/workspace/FeaturedMoE/experiments/run/AI502_transfer/artifacts_group1_best/hyperopt_results/ai502_transfer_group1_best/diag/raw/best_valid_diag.json",
  "diag_raw_best_valid_overview_file": "/workspace/FeaturedMoE/experiments/run/AI502_transfer/artifacts_group1_best/hyperopt_results/ai502_transfer_group1_best/diag/raw/best_valid_overview.json",
  "diag_raw_best_valid_overview_md_file": "/workspace/FeaturedMoE/experiments/run/AI502_transfer/artifacts_group1_best/hyperopt_results/ai502_transfer_group1_best/diag/raw/best_valid_overview.md",
  "diag_raw_early_valid_file": "/workspace/FeaturedMoE/experiments/run/AI502_transfer/artifacts_group1_best/hyperopt_results/ai502_transfer_group1_best/diag/raw/early_valid_diag.json",
  "diag_raw_test_file": "/workspace/FeaturedMoE/experiments/run/AI502_transfer/artifacts_group1_best/hyperopt_results/ai502_transfer_group1_best/diag/raw/test_diag.json",
  "diag_raw_collapse_file": "/workspace/FeaturedMoE/experiments/run/AI502_transfer/artifacts_group1_best/hyperopt_results/ai502_transfer_group1_best/diag/raw/collapse_diag.json",
  "diag_raw_epoch_trace_file": "/workspace/FeaturedMoE/experiments/run/AI502_transfer/artifacts_group1_best/hyperopt_results/ai502_transfer_group1_best/diag/raw/epoch_trace.csv",
  "feature_ablation_file": "",
  "logging_bundle_dir": "/workspace/FeaturedMoE/experiments/run/artifacts/logging/ai502_transfer_group1_best/retail_rocket/AI502/retail_rocket_FeaturedMoE_N3_ai502_g1_t_beauty_to_retail_rocket_retail_r10_h13_width_refine_full_model_init_l_20260507_175822_112572_pid619084",
  "logging_bundle_summary_file": "/workspace/FeaturedMoE/experiments/run/artifacts/logging/ai502_transfer_group1_best/retail_rocket/AI502/retail_rocket_FeaturedMoE_N3_ai502_g1_t_beauty_to_retail_rocket_retail_r10_h13_width_refine_full_model_init_l_20260507_175822_112572_pid619084/run_summary.json"
}
